README.md
setup.cfg
setup.py
shells_cae/__init__.py
shells_cae/al_tate_solver.py
shells_cae/apfsd_fl_stable_solver.py
shells_cae/eb3D_solver.py
shells_cae/eb_solver.py
shells_cae/geometry_solver.py
shells_cae/ib_solver.py
shells_cae/kontur_solver.py
shells_cae/mcc_solver.py
shells_cae/mcdrag_solver.py
shells_cae/penetration.py
shells_cae/solvers_abc.py
shells_cae/spinner_solver.py
shells_cae/strength_solver.py
shells_cae.egg-info/PKG-INFO
shells_cae.egg-info/SOURCES.txt
shells_cae.egg-info/dependency_links.txt
shells_cae.egg-info/not-zip-safe
shells_cae.egg-info/requires.txt
shells_cae.egg-info/top_level.txt
shells_cae/compiled/Spin73/libspinner.dll
shells_cae/compiled/al_tate_model/CMakeLists.txt
shells_cae/compiled/al_tate_model/src/penetration.f90
shells_cae/compiled/al_tate_model/src/test.f90
shells_cae/compiled/build/bin/ballistics.exe
shells_cae/compiled/build/bin/kontur_test.exe
shells_cae/compiled/build/bin/libkontur.dll
shells_cae/compiled/build/bin/libmcdrag.dll
shells_cae/compiled/build/bin/libpenetrationlib.dll
shells_cae/compiled/build/bin/libsextbal.dll
shells_cae/compiled/build/bin/libsintbal.dll
shells_cae/compiled/build/bin/mcdrag_lib.exe
shells_cae/compiled/external_3D_ballistics/ballistics3D.dll
shells_cae/compiled/external_ballistics/CMakeLists.txt
shells_cae/compiled/external_ballistics/src/solve_eb.f90
shells_cae/compiled/external_ballistics/src/solve_ebh.f90
shells_cae/compiled/internal_ballistics/CMakeLists.txt
shells_cae/compiled/internal_ballistics/src/ibstructs.f90
shells_cae/compiled/internal_ballistics/src/preproc.f90
shells_cae/compiled/internal_ballistics/src/solve_ib.f90
shells_cae/compiled/kontur/CMakeLists.txt
shells_cae/compiled/kontur/include/csv.h
shells_cae/compiled/kontur/include/kontur.h
shells_cae/compiled/kontur/include/structs.h
shells_cae/compiled/kontur/src/csv.c
shells_cae/compiled/kontur/src/csvstep.c
shells_cae/compiled/kontur/src/dcel.for
shells_cae/compiled/kontur/src/disco.for
shells_cae/compiled/kontur/src/geom.for
shells_cae/compiled/kontur/src/ggr.for
shells_cae/compiled/kontur/src/hybrid.for
shells_cae/compiled/kontur/src/inter5.for
shells_cae/compiled/kontur/src/interp.for
