Metadata-Version: 2.1
Name: shells-cae
Version: 0.0.34
Summary: Special CAЕ Library by sabbraxcaddabra&denchina
Author-email: denisdoronichev@outlook.com
Requires-Python: >=3.11
